mksir/AGGLOMERATIVE_MIN.ipynb
mksir/AgglomerativeWARDorAVG.ipynb
mksir/EasternConvert.ipynb
mksir/NEW_CLEANING_FOR_DATA.ipynb
mksir/OPractical3.ipynb
mksir/PRACTICAL_5.ipynb
mksir/Practical.ipynb
mksir/Practical1.ipynb
mksir/Practical6.ipynb
mksir/Practical_2.ipynb
mksir/Practical_4.ipynb
mksir/__init__.py
mksir/.ipynb_checkpoints/AGGLOMERATIVE_MIN-checkpoint.ipynb
mksir/.ipynb_checkpoints/AGGLOMERATIVE_MIN.ipynb
mksir/.ipynb_checkpoints/AgglomerativeWARDorAVG-checkpoint.ipynb
mksir/.ipynb_checkpoints/AgglomerativeWARDorAVG.ipynb
mksir/.ipynb_checkpoints/EasternConvert-checkpoint.ipynb
mksir/.ipynb_checkpoints/EasternConvert.ipynb
mksir/.ipynb_checkpoints/NEW_CLEANING_FOR_DATA-checkpoint.ipynb
mksir/.ipynb_checkpoints/NEW_CLEANING_FOR_DATA.ipynb
mksir/.ipynb_checkpoints/OPractical3-checkpoint.ipynb
mksir/.ipynb_checkpoints/OPractical3.ipynb
mksir/.ipynb_checkpoints/PRACTICAL_5-checkpoint.ipynb
mksir/.ipynb_checkpoints/PRACTICAL_5.ipynb
mksir/.ipynb_checkpoints/Practical-checkpoint.ipynb
mksir/.ipynb_checkpoints/Practical.ipynb
mksir/.ipynb_checkpoints/Practical1-checkpoint.ipynb
mksir/.ipynb_checkpoints/Practical1.ipynb
mksir/.ipynb_checkpoints/Practical6.ipynb
mksir/.ipynb_checkpoints/Practical_2-checkpoint.ipynb
mksir/.ipynb_checkpoints/Practical_2.ipynb
mksir/.ipynb_checkpoints/Practical_4-checkpoint.ipynb
mksir/.ipynb_checkpoints/Practical_4.ipynb
mksir-0.0.17.dist-info/METADATA
mksir-0.0.17.dist-info/WHEEL
mksir-0.0.17.dist-info/top_level.txt
mksir-0.0.17.dist-info/RECORD
