Metadata-Version: 2.1
Name: mksir
Version: 0.0.17
Summary: Data-mining tutorials
Author: Developer cheetah
Author-email: 
Keywords: datamining,tutorial,mksir
Classifier: Development Status :: 1 - Planning
Classifier: Intended Audience :: Developers
Classifier: Programming Language :: Python :: 3
Classifier: Operating System :: Unix
Classifier: Operating System :: MacOS :: MacOS X
Classifier: Operating System :: Microsoft :: Windows
